{
 "0.12.3-profiling": {
  "meta": {
   "description": "Binding to the GIO",
   "homepage": "http://projects.haskell.org/gtk2hs/",
   "license": {
    "fullName": "GNU Lesser General Public License version 2.1 only",
    "shortName": "LGPLv2.1",
    "url": "http://www.gnu.org/licenses/old-licenses/lgpl-2.1.html"
   },
   "long_description": "",
   "maintainers": [
    "Andres Loeh <ksnixos@andres-loeh.de>",
    "Peter Simons <simons@cryp.to>"
   ],
   "name": "haskell-gio-ghc7.0.4",
   "platforms": [
    "x86_64-linux",
    "i686-linux",
    "i686-darwin",
    "x86_64-darwin"
   ],
   "position": ""
  },
  "revs": [
   "0017d80aa50f8729b5a1e6c65c2f08971cafe526",
   "41840af6894bf718a1038ba1045adef26a687919"
  ]
 }
}