{
 "0.1": {
  "meta": {
   "description": "A Prolog interpreter written in Haskell",
   "homepage": "https://github.com/Erdwolf/prolog",
   "license": {
    "fullname": "Public Domain",
    "shortName": "Public Domain"
   },
   "long_description": "",
   "maintainers": [
    "Andres Loeh <ksnixos@andres-loeh.de>",
    "Peter Simons <simons@cryp.to>"
   ],
   "name": "haskell-prolog-ghc7.2.1",
   "platforms": [
    "x86_64-linux",
    "i686-linux"
   ],
   "position": ""
  },
  "revs": [
   "0009c1f650ba619de97df36322fbd0346db0c099",
   "5ec7aa7e71204504f684e37680d6a37adbc550ff"
  ]
 }
}