{
 "20130130": {
  "meta": {
   "description": "A movie player that supports many video formats (MPlayer fork)",
   "homepage": "http://mplayer2.org",
   "license": "GPLv3+",
   "long_description": "",
   "maintainers": [
    "Llu\u00eds Batlle i Rossell <viric@viric.name>"
   ],
   "name": "mplayer2",
   "platforms": [
    "i686-linux",
    "x86_64-linux",
    "powerpc-linux",
    "armv5tel-linux",
    "armv7l-linux",
    "mips64el-linux"
   ],
   "position": ""
  },
  "revs": [
   "00081d1873148a8ec642d5c912d04875c4ee4a66",
   "1a55c4b89f6f6e337d1ca8878bfd8104f3fb6304"
  ]
 },
 "20130428": {
  "meta": {
   "description": "A movie player that supports many video formats (MPlayer fork)",
   "homepage": "http://mplayer2.org",
   "license": {
    "fullName": "GNU General Public License v3.0 or later",
    "shortName": "GPL-3.0+",
    "url": "http://spdx.org/licenses/GPL-3.0+"
   },
   "long_description": "",
   "maintainers": [
    "Llu\u00eds Batlle i Rossell <viric@viric.name>"
   ],
   "name": "mplayer2",
   "platforms": [
    "i686-linux",
    "x86_64-linux",
    "armv5tel-linux",
    "armv7l-linux",
    "mips64el-linux"
   ],
   "position": "pkgs/applications/video/mplayer2/default.nix:131"
  },
  "revs": [
   "0005e1896d9bdef48aedcff9e86843351ac024e9",
   "6197fdc02d20763e10beb73c0b6384c255f142b2"
  ]
 }
}