{
 "0.0.35": {
  "meta": {
   "description": "Python port of Moses tokenizer, truecaser and normalizer",
   "homepage": "https://github.com/alvations/sacremoses",
   "license": {
    "fullName": "GNU Lesser General Public License v2.1 or later",
    "shortName": "lgpl21Plus",
    "spdxId": "LGPL-2.1-or-later",
    "url": "https://spdx.org/licenses/LGPL-2.1-or-later.html"
   },
   "long_description": "",
   "maintainers": [
    {
     "email": "pashashocky@gmail.com",
     "github": "pashashocky",
     "githubId": 673857,
     "name": "Pash Shocky"
    }
   ],
   "name": "python3.8-sacremoses",
   "platforms": [
    "x86_64-linux"
   ],
   "position": "pkgs/development/python-modules/sacremoses/default.nix:32"
  },
  "revs": [
   "00022fbeda385d7b6ae2eee44f07eecfc6d92015",
   "5101b357ec30c1ac4a9273b379e631f841af9fa3"
  ]
 }
}