{
 "0.8.0": {
  "meta": {
   "description": "Library to use HTTPSEverywhere in desktop applications",
   "homepage": "https://git.gnome.org/browse/libhttpseverywhere",
   "license": {
    "fullName": "GNU Lesser General Public License v3.0 only",
    "shortName": "lgpl3",
    "spdxId": "LGPL-3.0",
    "url": "http://spdx.org/licenses/LGPL-3.0.html"
   },
   "long_description": "",
   "maintainers": [
    {
     "email": "post@lukasepple.de",
     "github": "sternenseemann",
     "name": "Lukas Epple"
    },
    {
     "email": "lucabru@src.gnome.org",
     "github": "lethalman",
     "name": "Luca Bruno"
    },
    {
     "email": "jtojnar@gmail.com",
     "github": "jtojnar",
     "name": "Jan Tojnar"
    }
   ],
   "name": "libhttpseverywhere",
   "platforms": [
    "aarch64-linux",
    "armv5tel-linux",
    "armv6l-linux",
    "armv7l-linux",
    "mipsel-linux",
    "i686-linux",
    "x86_64-linux"
   ],
   "position": "pkgs/development/libraries/libhttpseverywhere/default.nix:33"
  },
  "revs": [
   "0008b5c2324b7dfc9420bdec9c8068f0755bf54f",
   "02a3726a1256fa0e144c302537c8b0876bfee77f"
  ]
 },
 "0.8.2": {
  "meta": {
   "description": "Library to use HTTPSEverywhere in desktop applications",
   "homepage": "https://git.gnome.org/browse/libhttpseverywhere",
   "license": {
    "fullName": "GNU Lesser General Public License v3.0 only",
    "shortName": "lgpl3",
    "spdxId": "LGPL-3.0",
    "url": "http://spdx.org/licenses/LGPL-3.0.html"
   },
   "long_description": "",
   "maintainers": [
    {
     "email": "post@lukasepple.de",
     "github": "sternenseemann",
     "name": "Lukas Epple"
    },
    {
     "email": "lucabru@src.gnome.org",
     "github": "lethalman",
     "name": "Luca Bruno"
    },
    {
     "email": "jtojnar@gmail.com",
     "github": "jtojnar",
     "name": "Jan Tojnar"
    }
   ],
   "name": "libhttpseverywhere",
   "platforms": [
    {
     "kernel": {
      "_type": "kernel",
      "execFormat": {
       "_type": "exec-format",
       "name": "elf"
      },
      "families": {},
      "name": "linux"
     }
    }
   ],
   "position": "pkgs/development/libraries/libhttpseverywhere/default.nix:35"
  },
  "revs": [
   "000482ffc470f798fb3aa1673b39a38680cbb567",
   "092deb9cf8378a0950574d714a60d7767da0fda1"
  ]
 },
 "0.8.3": {
  "meta": {
   "description": "Library to use HTTPSEverywhere in desktop applications",
   "homepage": "https://gitlab.gnome.org/GNOME/libhttpseverywhere",
   "license": {
    "fullName": "GNU Lesser General Public License v3.0 only",
    "shortName": "lgpl3",
    "spdxId": "LGPL-3.0",
    "url": "http://spdx.org/licenses/LGPL-3.0.html"
   },
   "long_description": "",
   "maintainers": [
    {
     "email": "post@lukasepple.de",
     "github": "sternenseemann",
     "name": "Lukas Epple"
    },
    {
     "email": "lucabru@src.gnome.org",
     "github": "lethalman",
     "name": "Luca Bruno"
    },
    {
     "email": "jtojnar@gmail.com",
     "github": "jtojnar",
     "name": "Jan Tojnar"
    },
    {
     "email": "torhedinbronner@gmail.com",
     "github": "hedning",
     "name": "Tor Hedin Br\u00f8nner"
    }
   ],
   "name": "libhttpseverywhere",
   "platforms": [
    {
     "kernel": {
      "_type": "kernel",
      "execFormat": {
       "_type": "exec-format",
       "name": "elf"
      },
      "families": {},
      "name": "linux"
     }
    }
   ],
   "position": "pkgs/development/libraries/libhttpseverywhere/default.nix:36"
  },
  "revs": [
   "00005ce0bdbc3c13804adc9a7fd71a02cc0b8db2",
   "01229007553d9322c473c0fa36e3d6c644147e7d"
  ]
 }
}