{
 "0.4.100.0": {
  "meta": {
   "description": "Near-future Sci-Fi roguelike and tactical squad game",
   "homepage": "http://allureofthestars.com",
   "license": "AGPL",
   "long_description": "",
   "maintainers": [],
   "name": "Allure",
   "platforms": [
    "x86_64-linux",
    "i686-linux",
    "x86_64-darwin"
   ],
   "position": "pkgs/games/Allure/default.nix:15"
  },
  "revs": [
   "0028f765f451c935c41106dda98c660ed41bdc29",
   "01910e84f9d16e1bff765d4dffb0defb4039bad6"
  ]
 },
 "0.4.99.0": {
  "meta": {
   "description": "Near-future Sci-Fi roguelike and tactical squad game",
   "homepage": "http://allureofthestars.com",
   "license": "unknown",
   "long_description": "",
   "maintainers": [],
   "name": "Allure",
   "platforms": [
    "x86_64-linux",
    "i686-linux",
    "i686-darwin",
    "x86_64-darwin"
   ],
   "position": "pkgs/games/Allure/default.nix:15"
  },
  "revs": [
   "0005e1896d9bdef48aedcff9e86843351ac024e9",
   "020b204767bb099702b5f27e263b37a2ecc16f93"
  ]
 }
}