{
 "0.10.4": {
  "meta": {
   "description": "A client library for the D-Bus IPC system",
   "homepage": "https://john-millikin.com/software/haskell-dbus/",
   "license": {
    "fullName": "GNU General Public License version 3 only",
    "shortName": "GPLv3",
    "url": "http://www.fsf.org/licensing/licenses/gpl.html"
   },
   "long_description": "",
   "maintainers": [],
   "name": "haskell-dbus-ghc7.6.3",
   "platforms": [
    "x86_64-linux",
    "i686-linux",
    "i686-darwin",
    "x86_64-darwin"
   ],
   "position": ""
  },
  "revs": [
   "000962c3fb53dcbe07e365875623d2d19fb4cdf6",
   "001550d5fe4174d081430d0da3790a815192eff6"
  ]
 },
 "0.10.5": {
  "meta": {
   "description": "A client library for the D-Bus IPC system",
   "homepage": "https://john-millikin.com/software/haskell-dbus/",
   "license": {
    "fullName": "GNU General Public License version 3 only",
    "shortName": "GPLv3",
    "url": "http://www.fsf.org/licensing/licenses/gpl.html"
   },
   "long_description": "",
   "maintainers": [],
   "name": "haskell-dbus-ghc7.6.3",
   "platforms": [
    "x86_64-linux",
    "i686-linux",
    "i686-darwin",
    "x86_64-darwin"
   ],
   "position": ""
  },
  "revs": [
   "00081d1873148a8ec642d5c912d04875c4ee4a66",
   "00081d1873148a8ec642d5c912d04875c4ee4a66"
  ]
 },
 "0.10.7": {
  "meta": {
   "description": "A client library for the D-Bus IPC system",
   "homepage": "https://john-millikin.com/software/haskell-dbus/",
   "license": {
    "fullName": "GNU General Public License version 3 only",
    "shortName": "GPLv3",
    "url": "http://www.fsf.org/licensing/licenses/gpl.html"
   },
   "long_description": "",
   "maintainers": [],
   "name": "haskell-dbus-ghc7.6.3",
   "platforms": [
    "x86_64-linux",
    "i686-linux",
    "i686-darwin",
    "x86_64-darwin"
   ],
   "position": "pkgs/development/libraries/haskell/dbus/default.nix:22"
  },
  "revs": [
   "0008a4b6c467977469b9b3bdec15fcc580204145",
   "00312d90b9ae42ae383174fcb6b4760d009606ed"
  ]
 },
 "0.10.8": {
  "meta": {
   "description": "A client library for the D-Bus IPC system",
   "homepage": "https://john-millikin.com/software/haskell-dbus/",
   "license": {
    "fullName": "GNU General Public License version 3 only",
    "shortName": "GPLv3",
    "url": "http://www.fsf.org/licensing/licenses/gpl.html"
   },
   "long_description": "",
   "maintainers": [],
   "name": "haskell-dbus-ghc7.6.3",
   "platforms": [
    "x86_64-linux",
    "i686-linux",
    "i686-darwin",
    "x86_64-darwin"
   ],
   "position": "pkgs/development/libraries/haskell/dbus/default.nix:22"
  },
  "revs": [
   "002d33b6ccdc90628799406c19b15648ca7e8349",
   "002d33b6ccdc90628799406c19b15648ca7e8349"
  ]
 },
 "0.10.8-shared": {
  "meta": {
   "description": "A client library for the D-Bus IPC system",
   "homepage": "https://john-millikin.com/software/haskell-dbus/",
   "license": {
    "fullName": "GNU General Public License v3.0 only",
    "shortName": "GPL-3.0",
    "url": "http://spdx.org/licenses/GPL-3.0"
   },
   "long_description": "",
   "maintainers": [],
   "name": "haskell-dbus-ghc7.8.3",
   "platforms": [
    "x86_64-linux",
    "i686-linux",
    "i686-darwin",
    "x86_64-darwin"
   ],
   "position": "pkgs/development/libraries/haskell/dbus/default.nix:24"
  },
  "revs": [
   "0005e1896d9bdef48aedcff9e86843351ac024e9",
   "0021ffab7a55237200bc9dd9e7096e70e28cdd0e"
  ]
 },
 "0.10.9-shared": {
  "meta": {
   "description": "A client library for the D-Bus IPC system",
   "homepage": "https://john-millikin.com/software/haskell-dbus/",
   "license": {
    "fullName": "GNU General Public License v3.0 only",
    "shortName": "gpl3",
    "spdxId": "GPL-3.0",
    "url": "http://spdx.org/licenses/GPL-3.0"
   },
   "long_description": "",
   "maintainers": [],
   "name": "haskell-dbus-ghc7.8.4",
   "platforms": [
    "x86_64-linux",
    "i686-linux",
    "x86_64-darwin"
   ],
   "position": "pkgs/development/libraries/haskell/dbus/default.nix:24"
  },
  "revs": [
   "001befaa6fb54b780254e7a7a6a5fc38051ccda0",
   "00230c92402bb3d94eae0db63cd6d2ba237b541f"
  ]
 }
}