{
 "0.1.2": {
  "meta": {
   "description": "Simple 3D vector library",
   "homepage": "",
   "license": "GPL",
   "long_description": "",
   "maintainers": [
    "Andres Loeh <andres@cs.uu.nl>"
   ],
   "name": "haskell-GlomeVec-ghc6.12.3",
   "platforms": null,
   "position": ""
  },
  "revs": [
   "0003f76f9b29d92ce7acb8e3f35f3805c91687d6",
   "0c8372d9c7374eafc035718749d81b8e8317f62e"
  ]
 },
 "0.2": {
  "meta": {
   "description": "Simple 3D vector library",
   "homepage": "http://www.haskell.org/haskellwiki/Glome",
   "license": "GPL",
   "long_description": "",
   "maintainers": [
    "Andres Loeh <ksnixos@andres-loeh.de>"
   ],
   "name": "haskell-GlomeVec-ghc7.6.3",
   "platforms": [
    "x86_64-linux",
    "i686-linux",
    "i686-darwin",
    "x86_64-darwin"
   ],
   "position": "pkgs/development/libraries/haskell/GlomeVec/default.nix:9"
  },
  "revs": [
   "0008a4b6c467977469b9b3bdec15fcc580204145",
   "0e04ba396ed174a70a894abb71b0a8f28c8caacf"
  ]
 },
 "0.2-shared": {
  "meta": {
   "description": "Simple 3D vector library",
   "homepage": "http://www.haskell.org/haskellwiki/Glome",
   "license": "GPL",
   "long_description": "",
   "maintainers": [],
   "name": "haskell-GlomeVec-ghc7.8.3",
   "platforms": [
    "x86_64-linux",
    "i686-linux",
    "i686-darwin",
    "x86_64-darwin"
   ],
   "position": "pkgs/development/libraries/haskell/GlomeVec/default.nix:12"
  },
  "revs": [
   "0005e1896d9bdef48aedcff9e86843351ac024e9",
   "0144849f678f9ff611c2a2f1538a455bb8ebdf69"
  ]
 }
}