{
 "0.1.2": {
  "meta": {
   "description": "Command-line argument parsing library for Haskell programs",
   "homepage": "",
   "license": null,
   "long_description": "",
   "maintainers": [],
   "name": "haskell-parseargs-ghc6.12.3",
   "platforms": null,
   "position": ""
  },
  "revs": [
   "0069aa0637dc1eab64c876e1d9b10117c3cac2e3",
   "049191511c0da8ad0e8fc74bc9e34bbd59cb6c9d"
  ]
 },
 "0.1.3.2": {
  "meta": {
   "description": "Command-line argument parsing library for Haskell programs",
   "homepage": "http://wiki.cs.pdx.edu/bartforge/parseargs",
   "license": {
    "fullName": "BSD license (3 clause)",
    "shortName": "BSD-3",
    "url": "http://www.opensource.org/licenses/bsd-license.php"
   },
   "long_description": "",
   "maintainers": [
    "Andres Loeh <ksnixos@andres-loeh.de>",
    "Peter Simons <simons@cryp.to>"
   ],
   "name": "haskell-parseargs-ghc6.12.3",
   "platforms": [
    "i686-darwin",
    "x86_64-linux",
    "i686-linux"
   ],
   "position": ""
  },
  "revs": [
   "000051b196b82d30d1008c8999502c484ea5bd7d",
   "283164779b9671517cfa9155abf57492129c95ad"
  ]
 },
 "0.1.3.4": {
  "meta": {
   "description": "Command-line argument parsing library for Haskell programs",
   "homepage": "http://wiki.cs.pdx.edu/bartforge/parseargs",
   "license": {
    "fullName": "BSD license (3 clause)",
    "shortName": "BSD-3",
    "url": "http://www.opensource.org/licenses/bsd-license.php"
   },
   "long_description": "",
   "maintainers": [
    "Andres Loeh <ksnixos@andres-loeh.de>"
   ],
   "name": "haskell-parseargs-ghc6.12.3",
   "platforms": [
    "i686-darwin",
    "x86_64-linux",
    "i686-linux"
   ],
   "position": ""
  },
  "revs": [
   "0072c442557b4d57fe128bf75775b2912f94b313",
   "090b8ea36f516ad5675f11671bf3f8b2966ac3c4"
  ]
 }
}