{
 "0.11.2": {
  "meta": {
   "description": "Pythonic API to Linux uinput kernel module",
   "homepage": "http://tjjr.fi/sw/python-uinput/",
   "license": {
    "fullName": "GNU General Public License v3.0 or later",
    "shortName": "gpl3Plus",
    "spdxId": "GPL-3.0+",
    "url": "http://spdx.org/licenses/GPL-3.0+"
   },
   "long_description": "",
   "maintainers": [
    "Nikolay Amiantov <ab@fmap.me>",
    "Florian Friesdorf <flo@chaoflow.net>",
    "Domen Kozar <domen@dev.si>"
   ],
   "name": "python3.5-python-uinput",
   "platforms": [
    "i686-linux",
    "x86_64-linux",
    "armv5tel-linux",
    "armv6l-linux",
    "armv7l-linux",
    "mips64el-linux",
    "x86_64-darwin"
   ],
   "position": "pkgs/top-level/python-packages.nix:746"
  },
  "revs": [
   "000fb9be33528f867e2355ddedde0836ba7f7a3a",
   "7731621c81b5cd601a176c2109b44c5295049f20"
  ]
 }
}